<?xml version="1.0" encoding="UTF-8" ?>
<odoo>
    <record model="ir.ui.view" id="partner_form">
        <field name="model">res.partner</field>
        <field name="inherit_id" ref="base.view_partner_form" />
        <field
            name="groups_id"
            eval="[(4, ref('agreement_legal.group_agreement_user'))]"
        />
        <field name="arch" type="xml">
            <xpath expr="//page[@name='internal_notes']" position="after">
                <page name="agreement" string="Agreements">
                    <group>
                        <field name="agreement_ids" nolabel="1" />
                    </group>
                </page>
            </xpath>
        </field>
    </record>
</odoo>
